MANIFEST.in
company_view.xml
data.xml
default_header.html
header_view.xml
ir_report_view.xml
setup.py
./__init__.py
./__openerp__.py
./company.py
./convert.py
./header.py
./ir_report.py
./report_helper.py
./webkit_report.py
./wizard/__init__.py
./wizard/report_webkit_actions.py
i18n/ar.po
i18n/bg.po
i18n/ca.po
i18n/cs.po
i18n/da.po
i18n/de.po
i18n/es.po
i18n/es_CR.po
i18n/es_MX.po
i18n/es_VE.po
i18n/fi.po
i18n/fr.po
i18n/hr.po
i18n/hu.po
i18n/it.po
i18n/ja.po
i18n/mk.po
i18n/mn.po
i18n/nl.po
i18n/pl.po
i18n/pt.po
i18n/pt_BR.po
i18n/report_webkit.pot
i18n/ro.po
i18n/ru.po
i18n/sl.po
i18n/sv.po
i18n/tr.po
i18n/zh_CN.po
images/companies_webkit.jpeg
images/header_html.jpeg
images/header_img.jpeg
openerp_report_webkit.egg-info/PKG-INFO
openerp_report_webkit.egg-info/SOURCES.txt
openerp_report_webkit.egg-info/dependency_links.txt
openerp_report_webkit.egg-info/requires.txt
openerp_report_webkit.egg-info/top_level.txt
security/ir.model.access.csv
wizard/report_webkit_actions_view.xml